[{"code":"001","name":"神保町","name_k":"ジンボウチヨウ","name_h":"じんぼうちよう","name_e":"jinbouchiyou"},{"code":"005","name":"春日部","name_k":"カスカベ","name_h":"かすかべ","name_e":"kasukabe"},{"code":"007","name":"新潟","name_k":"ニイガタ","name_h":"にいがた","name_e":"niigata"},{"code":"008","name":"長野","name_k":"ナガノ","name_h":"ながの","name_e":"nagano"},{"code":"009","name":"上田","name_k":"ウエダ","name_h":"うえだ","name_e":"ueda"},{"code":"012","name":"牛久","name_k":"ウシク","name_h":"うしく","name_e":"ushiku"},{"code":"015","name":"東京中央","name_k":"トウキヨウチユウオウ","name_h":"とうきようちゆうおう","name_e":"toukiyouchiyuuou"},{"code":"018","name":"諏訪","name_k":"スワ","name_h":"すわ","name_e":"suwa"},{"code":"020","name":"矢向","name_k":"ヤコウ","name_h":"やこう","name_e":"yakou"},{"code":"022","name":"小山","name_k":"オヤマ","name_h":"おやま","name_e":"oyama"},{"code":"026","name":"銀座","name_k":"ギンザ","name_h":"ぎんざ","name_e":"ginza"},{"code":"027","name":"前橋","name_k":"マエバシ","name_h":"まえばし","name_e":"maebashi"},{"code":"029","name":"亀有","name_k":"カメアリ","name_h":"かめあり","name_e":"kameari"},{"code":"030","name":"喜多見","name_k":"キタミ","name_h":"きたみ","name_e":"kitami"},{"code":"031","name":"氷川台","name_k":"ヒカワダイ","name_h":"ひかわだい","name_e":"hikawadai"},{"code":"032","name":"太田","name_k":"オオタ","name_h":"おおた","name_e":"oota"},{"code":"034","name":"日本橋東","name_k":"ニホンバシヒガシ","name_h":"にほんばしひがし","name_e":"nihonbashihigashi"},{"code":"038","name":"熊谷","name_k":"クマガヤ","name_h":"くまがや","name_e":"kumagaya"},{"code":"039","name":"川口","name_k":"カワグチ","name_h":"かわぐち","name_e":"kawaguchi"},{"code":"040","name":"浦和","name_k":"ウラワ","name_h":"うらわ","name_e":"urawa"},{"code":"045","name":"大阪公務部","name_k":"オオサカコウムブ","name_h":"おおさかこうむぶ","name_e":"oosakakoumubu"},{"code":"056","name":"桶川","name_k":"オケガワ","name_h":"おけがわ","name_e":"okegawa"},{"code":"057","name":"上福岡","name_k":"カミフクオカ","name_h":"かみふくおか","name_e":"kamifukuoka"},{"code":"058","name":"坂戸","name_k":"サカド","name_h":"さかど","name_e":"sakado"},{"code":"064","name":"練馬","name_k":"ネリマ","name_h":"ねりま","name_e":"nerima"},{"code":"066","name":"千葉","name_k":"チバ","name_h":"ちば","name_e":"chiba"},{"code":"070","name":"習志野","name_k":"ナラシノ","name_h":"ならしの","name_e":"narashino"},{"code":"073","name":"あやめ","name_k":"アヤメ","name_h":"あやめ","name_e":"ayame"},{"code":"074","name":"木更津","name_k":"キサラヅ","name_h":"きさらづ","name_e":"kisaradu"},{"code":"075","name":"佐倉","name_k":"サクラ","name_h":"さくら","name_e":"sakura"},{"code":"077","name":"本八幡","name_k":"モトヤワタ","name_h":"もとやわた","name_e":"motoyawata"},{"code":"078","name":"四街道","name_k":"ヨツカイドウ","name_h":"よつかいどう","name_e":"yotsukaidou"},{"code":"081","name":"千葉ニュータウン","name_k":"チバニユ-タウン","name_h":"ちばにゆ-たうん","name_e":"chibaniyu-taun"},{"code":"082","name":"西荻窪","name_k":"ニシオギクボ","name_h":"にしおぎくぼ","name_e":"nishiogikubo"},{"code":"089","name":"高円寺","name_k":"コウエンジ","name_h":"こうえんじ","name_e":"kouenji"},{"code":"094","name":"学芸大学駅前","name_k":"ガクダイマエ","name_h":"がくだいまえ","name_e":"gakudaimae"},{"code":"096","name":"東京公務部","name_k":"トウキヨウコウムブ","name_h":"とうきようこうむぶ","name_e":"toukiyoukoumubu"},{"code":"097","name":"蒲田西","name_k":"カマタニシ","name_h":"かまたにし","name_e":"kamatanishi"},{"code":"099","name":"旗ノ台","name_k":"ハタノダイ","name_h":"はたのだい","name_e":"hatanodai"},{"code":"101","name":"大阪本店営業部","name_k":"オオサカホンテン","name_h":"おおさかほんてん","name_e":"oosakahonten"},{"code":"103","name":"備後町","name_k":"ビンゴマチ","name_h":"びんごまち","name_e":"bingomachi"},{"code":"105","name":"今里","name_k":"イマザト","name_h":"いまざと","name_e":"imazato"},{"code":"106","name":"上町","name_k":"ウエマチ","name_h":"うえまち","name_e":"uemachi"},{"code":"107","name":"鶴橋","name_k":"ツルハシ","name_h":"つるはし","name_e":"tsuruhashi"},{"code":"109","name":"生野","name_k":"イクノ","name_h":"いくの","name_e":"ikuno"},{"code":"110","name":"玉造","name_k":"タマツクリ","name_h":"たまつくり","name_e":"tamatsukuri"},{"code":"111","name":"難波","name_k":"ナンバ","name_h":"なんば","name_e":"nanba"},{"code":"114","name":"天王寺駅前","name_k":"テンノウジエキマエ","name_h":"てんのうじえきまえ","name_e":"ten'noujiekimae"},{"code":"115","name":"美章園","name_k":"ビシヨウエン","name_h":"びしようえん","name_e":"bishiyouen"},{"code":"117","name":"粉浜","name_k":"コハマ","name_h":"こはま","name_e":"kohama"},{"code":"118","name":"平野","name_k":"ヒラノ","name_h":"ひらの","name_e":"hirano"},{"code":"119","name":"西野田","name_k":"ニシノダ","name_h":"にしのだ","name_e":"nishinoda"},{"code":"121","name":"港","name_k":"ミナト","name_h":"みなと","name_e":"minato"},{"code":"122","name":"船場","name_k":"センバ","name_h":"せんば","name_e":"senba"},{"code":"123","name":"立売堀","name_k":"イタチボリ","name_h":"いたちぼり","name_e":"itachibori"},{"code":"124","name":"大正区","name_k":"タイシヨウク","name_h":"たいしようく","name_e":"taishiyouku"},{"code":"125","name":"四貫島","name_k":"シカンジマ","name_h":"しかんじま","name_e":"shikanjima"},{"code":"126","name":"歌島橋","name_k":"ウタジマバシ","name_h":"うたじまばし","name_e":"utajimabashi"},{"code":"127","name":"梅田","name_k":"ウメダ","name_h":"うめだ","name_e":"umeda"},{"code":"129","name":"南森町","name_k":"ミナミモリマチ","name_h":"みなみもりまち","name_e":"minamimorimachi"},{"code":"130","name":"天六","name_k":"テンロク","name_h":"てんろく","name_e":"tenroku"},{"code":"131","name":"天満橋","name_k":"テンマバシ","name_h":"てんまばし","name_e":"tenmabashi"},{"code":"132","name":"城東","name_k":"ジヨウトウ","name_h":"じようとう","name_e":"jiyoutou"},{"code":"134","name":"十三","name_k":"ジユウソウ","name_h":"じゆうそう","name_e":"jiyuusou"},{"code":"138","name":"赤川町","name_k":"アカガワチヨウ","name_h":"あかがわちよう","name_e":"akagawachiyou"},{"code":"139","name":"京阪京橋","name_k":"ケイハンキヨウバシ","name_h":"けいはんきようばし","name_e":"keihankiyoubashi"},{"code":"140","name":"千林","name_k":"センバヤシ","name_h":"せんばやし","name_e":"senbayashi"},{"code":"141","name":"駒川町","name_k":"コマガワチヨウ","name_h":"こまがわちよう","name_e":"komagawachiyou"},{"code":"142","name":"洗足","name_k":"センゾク","name_h":"せんぞく","name_e":"senzoku"},{"code":"143","name":"寺田町","name_k":"テラダチヨウ","name_h":"てらだちよう","name_e":"teradachiyou"},{"code":"144","name":"深江橋","name_k":"フカエバシ","name_h":"ふかえばし","name_e":"fukaebashi"},{"code":"148","name":"大阪ビジネスパーク出張所","name_k":"オオサカビジネスパ-ク","name_h":"おおさかびじねすぱ-く","name_e":"oosakabijinesupa-ku"},{"code":"150","name":"砂町","name_k":"スナマチ","name_h":"すなまち","name_e":"sunamachi"},{"code":"151","name":"東大阪","name_k":"ヒガシオオサカ","name_h":"ひがしおおさか","name_e":"higashioosaka"},{"code":"152","name":"高槻","name_k":"タカツキ","name_h":"たかつき","name_e":"takatsuki"},{"code":"153","name":"池田","name_k":"イケダ","name_h":"いけだ","name_e":"ikeda"},{"code":"154","name":"豊中","name_k":"トヨナカ","name_h":"とよなか","name_e":"toyonaka"},{"code":"156","name":"守口","name_k":"モリグチ","name_h":"もりぐち","name_e":"moriguchi"},{"code":"157","name":"寝屋川","name_k":"ネヤガワ","name_h":"ねやがわ","name_e":"neyagawa"},{"code":"158","name":"枚方","name_k":"ヒラカタ","name_h":"ひらかた","name_e":"hirakata"},{"code":"159","name":"新石切","name_k":"シンイシキリ","name_h":"しんいしきり","name_e":"shin'ishikiri"},{"code":"160","name":"若江岩田","name_k":"ワカエイワタ","name_h":"わかえいわた","name_e":"wakaeiwata"},{"code":"161","name":"八尾","name_k":"ヤオ","name_h":"やお","name_e":"yao"},{"code":"162","name":"藤井寺","name_k":"フジイデラ","name_h":"ふじいでら","name_e":"fujiidera"},{"code":"163","name":"富田林","name_k":"トンダバヤシ","name_h":"とんだばやし","name_e":"tondabayashi"},{"code":"164","name":"河内長野","name_k":"カワチナガノ","name_h":"かわちながの","name_e":"kawachinagano"},{"code":"165","name":"徳庵","name_k":"トクアン","name_h":"とくあん","name_e":"tokuan"},{"code":"166","name":"小阪","name_k":"コサカ","name_h":"こさか","name_e":"kosaka"},{"code":"167","name":"庄内","name_k":"シヨウナイ","name_h":"しようない","name_e":"shiyounai"},{"code":"168","name":"門真","name_k":"カドマ","name_h":"かどま","name_e":"kadoma"},{"code":"169","name":"茨木","name_k":"イバラキ","name_h":"いばらき","name_e":"ibaraki"},{"code":"170","name":"松原","name_k":"マツバラ","name_h":"まつばら","name_e":"matsubara"},{"code":"171","name":"岸和田","name_k":"キシワダ","name_h":"きしわだ","name_e":"kishiwada"},{"code":"172","name":"港南台","name_k":"コウナンダイ","name_h":"こうなんだい","name_e":"kounandai"},{"code":"173","name":"逗子","name_k":"ズシ","name_h":"ずし","name_e":"zushi"},{"code":"174","name":"佐野","name_k":"サノ","name_h":"さの","name_e":"sano"},{"code":"175","name":"貝塚","name_k":"カイヅカ","name_h":"かいづか","name_e":"kaiduka"},{"code":"176","name":"泉大津","name_k":"イズミオオツ","name_h":"いずみおおつ","name_e":"izumiootsu"},{"code":"177","name":"和泉","name_k":"イズミ","name_h":"いずみ","name_e":"izumi"},{"code":"178","name":"堺","name_k":"サカイ","name_h":"さかい","name_e":"sakai"},{"code":"179","name":"浜寺","name_k":"ハマデラ","name_h":"はまでら","name_e":"hamadera"},{"code":"180","name":"鳳","name_k":"オオトリ","name_h":"おおとり","name_e":"ootori"},{"code":"181","name":"泉南","name_k":"センナン","name_h":"せんなん","name_e":"sen'nan"},{"code":"182","name":"箕面市役所出張所","name_k":"ミノオシヤクシヨ","name_h":"みのおしやくしよ","name_e":"minooshiyakushiyo"},{"code":"183","name":"くずは","name_k":"クズハ","name_h":"くずは","name_e":"kuzuha"},{"code":"184","name":"香里ヶ丘","name_k":"コウリガオカ","name_h":"こうりがおか","name_e":"kourigaoka"},{"code":"185","name":"箕面","name_k":"ミノオ","name_h":"みのお","name_e":"minoo"},{"code":"186","name":"はびきの出張所","name_k":"ハビキノ","name_h":"はびきの","name_e":"habikino"},{"code":"187","name":"泉北とが","name_k":"センボクトガ","name_h":"せんぼくとが","name_e":"senbokutoga"},{"code":"189","name":"南千里","name_k":"ミナミセンリ","name_h":"みなみせんり","name_e":"minamisenri"},{"code":"190","name":"町田山崎出張所","name_k":"マチダヤマザキ","name_h":"まちだやまざき","name_e":"machidayamazaki"},{"code":"191","name":"つきみ野","name_k":"ツキミノ","name_h":"つきみの","name_e":"tsukimino"},{"code":"192","name":"東豊中出張所","name_k":"ヒガシトヨナカ","name_h":"ひがしとよなか","name_e":"higashitoyonaka"},{"code":"193","name":"江坂","name_k":"エサカ","name_h":"えさか","name_e":"esaka"},{"code":"194","name":"金剛","name_k":"コンゴウ","name_h":"こんごう","name_e":"kongou"},{"code":"195","name":"石橋出張所","name_k":"イシバシ","name_h":"いしばし","name_e":"ishibashi"},{"code":"197","name":"守口市駅前出張所","name_k":"モリグチシエキマエ","name_h":"もりぐちしえきまえ","name_e":"moriguchishiekimae"},{"code":"198","name":"桜井出張所","name_k":"サクライ","name_h":"さくらい","name_e":"sakurai"},{"code":"200","name":"本店営業部","name_k":"ホンテン","name_h":"ほんてん","name_e":"honten"},{"code":"201","name":"取手","name_k":"トリデ","name_h":"とりで","name_e":"toride"},{"code":"204","name":"三ツ境","name_k":"ミツキヨウ","name_h":"みつきよう","name_e":"mitsukiyou"},{"code":"206","name":"行徳","name_k":"ギヨウトク","name_h":"ぎようとく","name_e":"giyoutoku"},{"code":"209","name":"サルビア","name_k":"サルビア","name_h":"さるびあ","name_e":"sarubia"},{"code":"210","name":"神戸公務部","name_k":"コウベコウムブ","name_h":"こうべこうむぶ","name_e":"koubekoumubu"},{"code":"211","name":"東京営業部","name_k":"トウキヨウエイギヨウブ","name_h":"とうきようえいぎようぶ","name_e":"toukiyoueigiyoubu"},{"code":"212","name":"人形町","name_k":"ニンギヨウチヨウ","name_h":"にんぎようちよう","name_e":"ningiyouchiyou"},{"code":"216","name":"新橋","name_k":"シンバシ","name_h":"しんばし","name_e":"shinbashi"},{"code":"217","name":"柿生","name_k":"カキオ","name_h":"かきお","name_e":"kakio"},{"code":"218","name":"麹町","name_k":"コウジマチ","name_h":"こうじまち","name_e":"koujimachi"},{"code":"219","name":"神田","name_k":"カンダ","name_h":"かんだ","name_e":"kanda"},{"code":"220","name":"神田駅前","name_k":"カンダエキマエ","name_h":"かんだえきまえ","name_e":"kandaekimae"},{"code":"221","name":"新宿","name_k":"シンジユク","name_h":"しんじゆく","name_e":"shinjiyuku"},{"code":"222","name":"成城","name_k":"セイジヨウ","name_h":"せいじよう","name_e":"seijiyou"},{"code":"223","name":"中野","name_k":"ナカノ","name_h":"なかの","name_e":"nakano"},{"code":"225","name":"池袋","name_k":"イケブクロ","name_h":"いけぶくろ","name_e":"ikebukuro"},{"code":"226","name":"赤羽","name_k":"アカバネ","name_h":"あかばね","name_e":"akabane"},{"code":"227","name":"大塚","name_k":"オオツカ","name_h":"おおつか","name_e":"ootsuka"},{"code":"228","name":"白山","name_k":"ハクサン","name_h":"はくさん","name_e":"hakusan"},{"code":"230","name":"浅草","name_k":"アサクサ","name_h":"あさくさ","name_e":"asakusa"},{"code":"231","name":"葛飾","name_k":"カツシカ","name_h":"かつしか","name_e":"katsushika"},{"code":"232","name":"新小岩","name_k":"シンコイワ","name_h":"しんこいわ","name_e":"shinkoiwa"},{"code":"234","name":"渋谷駅前","name_k":"シブヤエキマエ","name_h":"しぶやえきまえ","name_e":"shibuyaekimae"},{"code":"235","name":"都立大学駅前","name_k":"トリツダイガクエキマエ","name_h":"とりつだいがくえきまえ","name_e":"toritsudaigakuekimae"},{"code":"237","name":"田園調布","name_k":"デンエンチヨウフ","name_h":"でんえんちようふ","name_e":"den'enchiyoufu"},{"code":"238","name":"荏原","name_k":"エバラ","name_h":"えばら","name_e":"ebara"},{"code":"239","name":"蒲田","name_k":"カマタ","name_h":"かまた","name_e":"kamata"},{"code":"242","name":"いずみ野","name_k":"イズミノ","name_h":"いずみの","name_e":"izumino"},{"code":"244","name":"つくば","name_k":"ツクバ","name_h":"つくば","name_e":"tsukuba"},{"code":"245","name":"丸ノ内","name_k":"マルノウチ","name_h":"まるのうち","name_e":"marunouchi"},{"code":"247","name":"三鷹","name_k":"ミタカ","name_h":"みたか","name_e":"mitaka"},{"code":"248","name":"千住","name_k":"センジユ","name_h":"せんじゆ","name_e":"senjiyu"},{"code":"249","name":"中村橋","name_k":"ナカムラバシ","name_h":"なかむらばし","name_e":"nakamurabashi"},{"code":"254","name":"亀戸","name_k":"カメイド","name_h":"かめいど","name_e":"kameido"},{"code":"255","name":"下高井戸","name_k":"シモタカイド","name_h":"しもたかいど","name_e":"shimotakaido"},{"code":"258","name":"青山","name_k":"アオヤマ","name_h":"あおやま","name_e":"aoyama"},{"code":"259","name":"新宿西口","name_k":"シンジユクニシグチ","name_h":"しんじゆくにしぐち","name_e":"shinjiyukunishiguchi"},{"code":"261","name":"高幡不動","name_k":"タカハタフドウ","name_h":"たかはたふどう","name_e":"takahatafudou"},{"code":"266","name":"高島平","name_k":"タカシマダイラ","name_h":"たかしまだいら","name_e":"takashimadaira"},{"code":"268","name":"北野","name_k":"キタノ","name_h":"きたの","name_e":"kitano"},{"code":"270","name":"麻布","name_k":"アザブ","name_h":"あざぶ","name_e":"azabu"},{"code":"273","name":"高田馬場","name_k":"タカダノババ","name_h":"たかだのばば","name_e":"takadanobaba"},{"code":"276","name":"西葛西","name_k":"ニシカサイ","name_h":"にしかさい","name_e":"nishikasai"},{"code":"278","name":"トヨタビル出張所","name_k":"トヨタビル","name_h":"とよたびる","name_e":"toyotabiru"},{"code":"285","name":"日野","name_k":"ヒノ","name_h":"ひの","name_e":"hino"},{"code":"288","name":"光が丘","name_k":"ヒカリガオカ","name_h":"ひかりがおか","name_e":"hikarigaoka"},{"code":"290","name":"広尾","name_k":"ヒロオ","name_h":"ひろお","name_e":"hiroo"},{"code":"296","name":"武蔵境","name_k":"ムサシサカイ","name_h":"むさしさかい","name_e":"musashisakai"},{"code":"298","name":"緑園都市","name_k":"リヨクエントシ","name_h":"りよくえんとし","name_e":"riyokuentoshi"},{"code":"301","name":"札幌","name_k":"サツポロ","name_h":"さつぽろ","name_e":"satsuporo"},{"code":"302","name":"灘","name_k":"ナダ","name_h":"なだ","name_e":"nada"},{"code":"306","name":"甲南","name_k":"コウナン","name_h":"こうなん","name_e":"kounan"},{"code":"307","name":"住吉","name_k":"スミヨシ","name_h":"すみよし","name_e":"sumiyoshi"},{"code":"308","name":"御影","name_k":"ミカゲ","name_h":"みかげ","name_e":"mikage"},{"code":"311","name":"仙台","name_k":"センダイ","name_h":"せんだい","name_e":"sendai"},{"code":"313","name":"神戸駅前","name_k":"コウベエキマエ","name_h":"こうべえきまえ","name_e":"koubeekimae"},{"code":"315","name":"湊川","name_k":"ミナトガワ","name_h":"みなとがわ","name_e":"minatogawa"},{"code":"320","name":"兵庫","name_k":"ヒヨウゴ","name_h":"ひようご","name_e":"hiyougo"},{"code":"321","name":"横浜中央","name_k":"ヨコハマチユウオウ","name_h":"よこはまちゆうおう","name_e":"yokohamachiyuuou"},{"code":"322","name":"新横浜","name_k":"シンヨコハマ","name_h":"しんよこはま","name_e":"shin'yokohama"},{"code":"325","name":"船橋","name_k":"フナバシ","name_h":"ふなばし","name_e":"funabashi"},{"code":"329","name":"綱島","name_k":"ツナシマ","name_h":"つなしま","name_e":"tsunashima"},{"code":"330","name":"金沢文庫","name_k":"カナザワブンコ","name_h":"かなざわぶんこ","name_e":"kanazawabunko"},{"code":"332","name":"静岡","name_k":"シズオカ","name_h":"しずおか","name_e":"shizuoka"},{"code":"334","name":"たまプラーザ","name_k":"タマプラ-ザ","name_h":"たまぷら-ざ","name_e":"tamapura-za"},{"code":"337","name":"西神中央","name_k":"セイシンチユウオウ","name_h":"せいしんちゆうおう","name_e":"seishinchiyuuou"},{"code":"338","name":"神戸学園都市","name_k":"コウベガクエントシ","name_h":"こうべがくえんとし","name_e":"koubegakuentoshi"},{"code":"339","name":"六甲アイランド","name_k":"ロツコウアイランド","name_h":"ろつこうあいらんど","name_e":"rotsukouairando"},{"code":"341","name":"草加","name_k":"ソウカ","name_h":"そうか","name_e":"souka"},{"code":"344","name":"越谷","name_k":"コシガヤ","name_h":"こしがや","name_e":"koshigaya"},{"code":"345","name":"所沢","name_k":"トコロザワ","name_h":"ところざわ","name_e":"tokorozawa"},{"code":"346","name":"藤沢","name_k":"フジサワ","name_h":"ふじさわ","name_e":"fujisawa"},{"code":"347","name":"大和","name_k":"ヤマト","name_h":"やまと","name_e":"yamato"},{"code":"348","name":"鈴蘭台","name_k":"スズランダイ","name_h":"すずらんだい","name_e":"suzurandai"},{"code":"349","name":"新座志木","name_k":"ニイザシキ","name_h":"にいざしき","name_e":"niizashiki"},{"code":"351","name":"片瀬山出張所","name_k":"カタセヤマ","name_h":"かたせやま","name_e":"kataseyama"},{"code":"352","name":"百合ヶ丘出張所","name_k":"ユリガオカ","name_h":"ゆりがおか","name_e":"yurigaoka"},{"code":"353","name":"武蔵中原","name_k":"ムサシナカハラ","name_h":"むさしなかはら","name_e":"musashinakahara"},{"code":"354","name":"志木ニュータウン","name_k":"シキニユ-タウン","name_h":"しきにゆ-たうん","name_e":"shikiniyu-taun"},{"code":"355","name":"伊丹","name_k":"イタミ","name_h":"いたみ","name_e":"itami"},{"code":"356","name":"川西","name_k":"カワニシ","name_h":"かわにし","name_e":"kawanishi"},{"code":"360","name":"新百合ヶ丘","name_k":"シンユリガオカ","name_h":"しんゆりがおか","name_e":"shin'yurigaoka"},{"code":"362","name":"荻窪","name_k":"オギクボ","name_h":"おぎくぼ","name_e":"ogikubo"},{"code":"366","name":"金沢","name_k":"カナザワ","name_h":"かなざわ","name_e":"kanazawa"},{"code":"368","name":"板宿","name_k":"イタヤド","name_h":"いたやど","name_e":"itayado"},{"code":"369","name":"須磨","name_k":"スマ","name_h":"すま","name_e":"suma"},{"code":"370","name":"西宮","name_k":"ニシノミヤ","name_h":"にしのみや","name_e":"nishinomiya"},{"code":"371","name":"垂水","name_k":"タルミ","name_h":"たるみ","name_e":"tarumi"},{"code":"372","name":"甲子園口","name_k":"コウシエングチ","name_h":"こうしえんぐち","name_e":"koushienguchi"},{"code":"374","name":"夙川","name_k":"シユクガワ","name_h":"しゆくがわ","name_e":"shiyukugawa"},{"code":"375","name":"西宮北口","name_k":"ニシノミヤキタグチ","name_h":"にしのみやきたぐち","name_e":"nishinomiyakitaguchi"},{"code":"376","name":"甲東","name_k":"コウトウ","name_h":"こうとう","name_e":"koutou"},{"code":"377","name":"宝塚","name_k":"タカラヅカ","name_h":"たからづか","name_e":"takaraduka"},{"code":"378","name":"逆瀬川","name_k":"サカセガワ","name_h":"さかせがわ","name_e":"sakasegawa"},{"code":"379","name":"芦屋","name_k":"アシヤ","name_h":"あしや","name_e":"ashiya"},{"code":"380","name":"芦屋駅前","name_k":"アシヤエキマエ","name_h":"あしやえきまえ","name_e":"ashiyaekimae"},{"code":"382","name":"港北ニュータウン","name_k":"コウホクニユ-タウン","name_h":"こうほくにゆ-たうん","name_e":"kouhokuniyu-taun"},{"code":"387","name":"北鈴蘭台","name_k":"キタスズランダイ","name_h":"きたすずらんだい","name_e":"kitasuzurandai"},{"code":"390","name":"エーティーエム統括","name_k":"エ-テイ-エムトウカツ","name_h":"え-てい-えむとうかつ","name_e":"e-tei-emutoukatsu"},{"code":"391","name":"三田","name_k":"サンダ","name_h":"さんだ","name_e":"sanda"},{"code":"392","name":"篠山","name_k":"ササヤマ","name_h":"ささやま","name_e":"sasayama"},{"code":"394","name":"フラワータウン出張所","name_k":"フラワ-タウン","name_h":"ふらわ-たうん","name_e":"furawa-taun"},{"code":"395","name":"ウッディタウン出張所","name_k":"ウツデイタウン","name_h":"うつでいたうん","name_e":"utsudeitaun"},{"code":"396","name":"藤原台","name_k":"フジワラダイ","name_h":"ふじわらだい","name_e":"fujiwaradai"},{"code":"400","name":"長田","name_k":"ナガタ","name_h":"ながた","name_e":"nagata"},{"code":"402","name":"名古屋駅前","name_k":"ナゴヤエキマエ","name_h":"なごやえきまえ","name_e":"nagoyaekimae"},{"code":"404","name":"豊橋","name_k":"トヨハシ","name_h":"とよはし","name_e":"toyohashi"},{"code":"407","name":"岐阜","name_k":"ギフ","name_h":"ぎふ","name_e":"gifu"},{"code":"408","name":"名古屋栄","name_k":"ナゴヤサカエ","name_h":"なごやさかえ","name_e":"nagoyasakae"},{"code":"410","name":"三宮","name_k":"サンノミヤ","name_h":"さんのみや","name_e":"san'nomiya"},{"code":"411","name":"洲本","name_k":"スモト","name_h":"すもと","name_e":"sumoto"},{"code":"419","name":"尼崎","name_k":"アマガサキ","name_h":"あまがさき","name_e":"amagasaki"},{"code":"420","name":"塚口","name_k":"ツカグチ","name_h":"つかぐち","name_e":"tsukaguchi"},{"code":"421","name":"六甲","name_k":"ロツコウ","name_h":"ろつこう","name_e":"rotsukou"},{"code":"422","name":"園田","name_k":"ソノダ","name_h":"そのだ","name_e":"sonoda"},{"code":"423","name":"尼崎市役所出張所","name_k":"アマガサキシヤクシヨ","name_h":"あまがさきしやくしよ","name_e":"amagasakishiyakushiyo"},{"code":"424","name":"武庫之荘","name_k":"ムコノソウ","name_h":"むこのそう","name_e":"mukonosou"},{"code":"425","name":"明石","name_k":"アカシ","name_h":"あかし","name_e":"akashi"},{"code":"426","name":"大久保","name_k":"オオクボ","name_h":"おおくぼ","name_e":"ookubo"},{"code":"428","name":"兵庫県庁出張所","name_k":"ヒヨウゴケンチヨウ","name_h":"ひようごけんちよう","name_e":"hiyougokenchiyou"},{"code":"431","name":"加古川","name_k":"カコガワ","name_h":"かこがわ","name_e":"kakogawa"},{"code":"432","name":"東加古川","name_k":"ヒガシカコガワ","name_h":"ひがしかこがわ","name_e":"higashikakogawa"},{"code":"433","name":"別府","name_k":"ベフ","name_h":"べふ","name_e":"befu"},{"code":"435","name":"高砂","name_k":"タカサゴ","name_h":"たかさご","name_e":"takasago"},{"code":"436","name":"曽根出張所","name_k":"ソネ","name_h":"そね","name_e":"sone"},{"code":"438","name":"三木","name_k":"ミキ","name_h":"みき","name_e":"miki"},{"code":"441","name":"西脇","name_k":"ニシワキ","name_h":"にしわき","name_e":"nishiwaki"},{"code":"442","name":"緑が丘","name_k":"ミドリガオカ","name_h":"みどりがおか","name_e":"midorigaoka"},{"code":"443","name":"大阪西","name_k":"オオサカニシ","name_h":"おおさかにし","name_e":"oosakanishi"},{"code":"444","name":"北条","name_k":"ホウジヨウ","name_h":"ほうじよう","name_e":"houjiyou"},{"code":"448","name":"天下茶屋","name_k":"テンガチヤヤ","name_h":"てんがちやや","name_e":"tengachiyaya"},{"code":"449","name":"阿倍野","name_k":"アベノ","name_h":"あべの","name_e":"abeno"},{"code":"450","name":"西田辺","name_k":"ニシタナベ","name_h":"にしたなべ","name_e":"nishitanabe"},{"code":"451","name":"姫路","name_k":"ヒメジ","name_h":"ひめじ","name_e":"himeji"},{"code":"455","name":"飾磨","name_k":"シカマ","name_h":"しかま","name_e":"shikama"},{"code":"457","name":"広畑","name_k":"ヒロハタ","name_h":"ひろはた","name_e":"hirohata"},{"code":"458","name":"網干","name_k":"アボシ","name_h":"あぼし","name_e":"aboshi"},{"code":"461","name":"姫路市役所出張所","name_k":"ヒメジシヤクシヨ","name_h":"ひめじしやくしよ","name_e":"himejishiyakushiyo"},{"code":"463","name":"龍野","name_k":"タツノ","name_h":"たつの","name_e":"tatsuno"},{"code":"470","name":"豊岡","name_k":"トヨオカ","name_h":"とよおか","name_e":"toyooka"},{"code":"473","name":"甲府","name_k":"コウフ","name_h":"こうふ","name_e":"koufu"},{"code":"477","name":"浜松","name_k":"ハママツ","name_h":"はままつ","name_e":"hamamatsu"},{"code":"481","name":"名古屋","name_k":"ナゴヤ","name_h":"なごや","name_e":"nagoya"},{"code":"482","name":"上前津","name_k":"カミマエヅ","name_h":"かみまえづ","name_e":"kamimaedu"},{"code":"484","name":"本山","name_k":"モトヤマ","name_h":"もとやま","name_e":"motoyama"},{"code":"486","name":"刈谷","name_k":"カリヤ","name_h":"かりや","name_e":"kariya"},{"code":"487","name":"豊田","name_k":"トヨタ","name_h":"とよた","name_e":"toyota"},{"code":"491","name":"円町","name_k":"エンマチ","name_h":"えんまち","name_e":"enmachi"},{"code":"496","name":"京都","name_k":"キヨウト","name_h":"きようと","name_e":"kiyouto"},{"code":"497","name":"松戸","name_k":"マツド","name_h":"まつど","name_e":"matsudo"},{"code":"498","name":"柏","name_k":"カシワ","name_h":"かしわ","name_e":"kashiwa"},{"code":"500","name":"神戸営業部","name_k":"コウベ","name_h":"こうべ","name_e":"koube"},{"code":"501","name":"富山","name_k":"トヤマ","name_h":"とやま","name_e":"toyama"},{"code":"502","name":"福井","name_k":"フクイ","name_h":"ふくい","name_e":"fukui"},{"code":"505","name":"八千代","name_k":"ヤチヨ","name_h":"やちよ","name_e":"yachiyo"},{"code":"506","name":"新大阪","name_k":"シンオオサカ","name_h":"しんおおさか","name_e":"shin'oosaka"},{"code":"507","name":"川越","name_k":"カワゴエ","name_h":"かわごえ","name_e":"kawagoe"},{"code":"508","name":"鹿児島","name_k":"カゴシマ","name_h":"かごしま","name_e":"kagoshima"},{"code":"512","name":"四条","name_k":"シジヨウ","name_h":"しじよう","name_e":"shijiyou"},{"code":"513","name":"伏見","name_k":"フシミ","name_h":"ふしみ","name_e":"fushimi"},{"code":"514","name":"大宮","name_k":"オオミヤ","name_h":"おおみや","name_e":"oomiya"},{"code":"516","name":"小手指","name_k":"コテサシ","name_h":"こてさし","name_e":"kotesashi"},{"code":"517","name":"御堂筋","name_k":"ミドウスジ","name_h":"みどうすじ","name_e":"midousuji"},{"code":"518","name":"堂島","name_k":"ドウジマ","name_h":"どうじま","name_e":"doujima"},{"code":"526","name":"岡本","name_k":"オカモト","name_h":"おかもと","name_e":"okamoto"},{"code":"527","name":"高槻駅前","name_k":"タカツキエキマエ","name_h":"たかつきえきまえ","name_e":"takatsukiekimae"},{"code":"533","name":"杭瀬","name_k":"クイセ","name_h":"くいせ","name_e":"kuise"},{"code":"536","name":"立花","name_k":"タチバナ","name_h":"たちばな","name_e":"tachibana"},{"code":"541","name":"奈良","name_k":"ナラ","name_h":"なら","name_e":"nara"},{"code":"542","name":"和歌山","name_k":"ワカヤマ","name_h":"わかやま","name_e":"wakayama"},{"code":"543","name":"平城","name_k":"ヘイジヨウ","name_h":"へいじよう","name_e":"heijiyou"},{"code":"544","name":"大和郡山","name_k":"ヤマトコオリヤマ","name_h":"やまとこおりやま","name_e":"yamatokooriyama"},{"code":"546","name":"学園前","name_k":"ガクエンマエ","name_h":"がくえんまえ","name_e":"gakuenmae"},{"code":"547","name":"横浜駅前","name_k":"ヨコハマエキマエ","name_h":"よこはまえきまえ","name_e":"yokohamaekimae"},{"code":"548","name":"成田","name_k":"ナリタ","name_h":"なりた","name_e":"narita"},{"code":"549","name":"浦安","name_k":"ウラヤス","name_h":"うらやす","name_e":"urayasu"},{"code":"551","name":"板橋","name_k":"イタバシ","name_h":"いたばし","name_e":"itabashi"},{"code":"556","name":"千里中央","name_k":"センリチユウオウ","name_h":"せんりちゆうおう","name_e":"senrichiyuuou"},{"code":"558","name":"中もず","name_k":"ナカモズ","name_h":"なかもず","name_e":"nakamozu"},{"code":"559","name":"茨木西","name_k":"イバラキニシ","name_h":"いばらきにし","name_e":"ibarakinishi"},{"code":"560","name":"コスモタワー出張所","name_k":"コスモタワ-","name_h":"こすもたわ-","name_e":"kosumotawa-"},{"code":"563","name":"山本","name_k":"ヤマモト","name_h":"やまもと","name_e":"yamamoto"},{"code":"564","name":"ひばりヶ丘","name_k":"ヒバリガオカ","name_h":"ひばりがおか","name_e":"hibarigaoka"},{"code":"565","name":"平塚","name_k":"ヒラツカ","name_h":"ひらつか","name_e":"hiratsuka"},{"code":"566","name":"上大岡","name_k":"カミオオオカ","name_h":"かみおおおか","name_e":"kamioooka"},{"code":"567","name":"金沢八景","name_k":"カナザワハツケイ","name_h":"かなざわはつけい","name_e":"kanazawahatsukei"},{"code":"568","name":"二俣川","name_k":"フタマタガワ","name_h":"ふたまたがわ","name_e":"futamatagawa"},{"code":"572","name":"鶴見","name_k":"ツルミ","name_h":"つるみ","name_e":"tsurumi"},{"code":"573","name":"あざみ野","name_k":"アザミノ","name_h":"あざみの","name_e":"azamino"},{"code":"578","name":"東神奈川","name_k":"ヒガシカナガワ","name_h":"ひがしかながわ","name_e":"higashikanagawa"},{"code":"579","name":"青葉台","name_k":"アオバダイ","name_h":"あおばだい","name_e":"aobadai"},{"code":"582","name":"甲子園","name_k":"コウシエン","name_h":"こうしえん","name_e":"koushien"},{"code":"586","name":"わらび","name_k":"ワラビ","name_h":"わらび","name_e":"warabi"},{"code":"588","name":"横浜","name_k":"ヨコハマ","name_h":"よこはま","name_e":"yokohama"},{"code":"593","name":"東京ディズニーランド出張所","name_k":"デイズニ-ランド","name_h":"でいずに-らんど","name_e":"deizuni-rando"},{"code":"595","name":"厚木","name_k":"アツギ","name_h":"あつぎ","name_e":"atsugi"},{"code":"596","name":"溝ノ口","name_k":"ミゾノクチ","name_h":"みぞのくち","name_e":"mizonokuchi"},{"code":"597","name":"経堂","name_k":"キヨウドウ","name_h":"きようどう","name_e":"kiyoudou"},{"code":"598","name":"神戸市役所出張所","name_k":"コウベシヤクシヨ","name_h":"こうべしやくしよ","name_e":"koubeshiyakushiyo"},{"code":"602","name":"尾道","name_k":"オノミチ","name_h":"おのみち","name_e":"onomichi"},{"code":"603","name":"新居浜","name_k":"ニイハマ","name_h":"にいはま","name_e":"niihama"},{"code":"605","name":"広島","name_k":"ヒロシマ","name_h":"ひろしま","name_e":"hiroshima"},{"code":"607","name":"ＡＴＭサービス東日本第一","name_k":"エ-テイ-エムヒガシイチ","name_h":"え-てい-えむひがしいち","name_e":"e-tei-emuhigashiichi"},{"code":"608","name":"大泉","name_k":"オオイズミ","name_h":"おおいずみ","name_e":"ooizumi"},{"code":"614","name":"浅草橋","name_k":"アサクサバシ","name_h":"あさくさばし","name_e":"asakusabashi"},{"code":"615","name":"錦糸町","name_k":"キンシチヨウ","name_h":"きんしちよう","name_e":"kinshichiyou"},{"code":"619","name":"六本木","name_k":"ロツポンギ","name_h":"ろつぽんぎ","name_e":"rotsupongi"},{"code":"623","name":"三田通","name_k":"ミタドオリ","name_h":"みたどおり","name_e":"mitadoori"},{"code":"624","name":"ＡＴＭサービス東日本第二","name_k":"エ-テイ-エムヒガシニ","name_h":"え-てい-えむひがしに","name_e":"e-tei-emuhigashini"},{"code":"625","name":"築地","name_k":"ツキジ","name_h":"つきじ","name_e":"tsukiji"},{"code":"626","name":"下井草","name_k":"シモイグサ","name_h":"しもいぐさ","name_e":"shimoigusa"},{"code":"627","name":"花小金井","name_k":"ハナコガネイ","name_h":"はなこがねい","name_e":"hanakoganei"},{"code":"628","name":"府中","name_k":"フチユウ","name_h":"ふちゆう","name_e":"fuchiyuu"},{"code":"629","name":"ＡＴＭサービス東日本第三","name_k":"エ-テイ-エムヒガシサン","name_h":"え-てい-えむひがしさん","name_e":"e-tei-emuhigashisan"},{"code":"632","name":"日比谷","name_k":"ヒビヤ","name_h":"ひびや","name_e":"hibiya"},{"code":"633","name":"雪ヶ谷","name_k":"ユキガヤ","name_h":"ゆきがや","name_e":"yukigaya"},{"code":"637","name":"京橋","name_k":"キヨウバシ","name_h":"きようばし","name_e":"kiyoubashi"},{"code":"638","name":"永福町","name_k":"エイフクチヨウ","name_h":"えいふくちよう","name_e":"eifukuchiyou"},{"code":"639","name":"霞が関","name_k":"カスミガセキ","name_h":"かすみがせき","name_e":"kasumigaseki"},{"code":"643","name":"小岩","name_k":"コイワ","name_h":"こいわ","name_e":"koiwa"},{"code":"644","name":"ＡＴＭサービス東日本第四","name_k":"エ-テイ-エムヒガシヨン","name_h":"え-てい-えむひがしよん","name_e":"e-tei-emuhigashiyon"},{"code":"647","name":"日暮里","name_k":"ニツポリ","name_h":"につぽり","name_e":"nitsupori"},{"code":"648","name":"町屋","name_k":"マチヤ","name_h":"まちや","name_e":"machiya"},{"code":"649","name":"西新井","name_k":"ニシアライ","name_h":"にしあらい","name_e":"nishiarai"},{"code":"651","name":"岡山","name_k":"オカヤマ","name_h":"おかやま","name_e":"okayama"},{"code":"653","name":"五反田","name_k":"ゴタンダ","name_h":"ごたんだ","name_e":"gotanda"},{"code":"654","name":"渋谷","name_k":"シブヤ","name_h":"しぶや","name_e":"shibuya"},{"code":"655","name":"自由が丘","name_k":"ジユウガオカ","name_h":"じゆうがおか","name_e":"jiyuugaoka"},{"code":"656","name":"恵比寿","name_k":"エビス","name_h":"えびす","name_e":"ebisu"},{"code":"658","name":"桜新町","name_k":"サクラシンマチ","name_h":"さくらしんまち","name_e":"sakurashinmachi"},{"code":"661","name":"新宿通","name_k":"シンジユクドオリ","name_h":"しんじゆくどおり","name_e":"shinjiyukudoori"},{"code":"662","name":"ＡＴＭサービス東日本第五","name_k":"エ-テイ-エムヒガシゴ","name_h":"え-てい-えむひがしご","name_e":"e-tei-emuhigashigo"},{"code":"663","name":"ＡＴＭサービス東日本第六","name_k":"エ-テイ-エムヒガシロク","name_h":"え-てい-えむひがしろく","name_e":"e-tei-emuhigashiroku"},{"code":"664","name":"ＡＴＭサービス東日本第七","name_k":"エ-テイ-エムヒガシナナ","name_h":"え-てい-えむひがしなな","name_e":"e-tei-emuhigashinana"},{"code":"665","name":"武蔵関","name_k":"ムサシセキ","name_h":"むさしせき","name_e":"musashiseki"},{"code":"666","name":"国立","name_k":"クニタチ","name_h":"くにたち","name_e":"kunitachi"},{"code":"667","name":"ＡＴＭサービス東日本第八","name_k":"エ-テイ-エムヒガシハチ","name_h":"え-てい-えむひがしはち","name_e":"e-tei-emuhigashihachi"},{"code":"669","name":"幡ヶ谷","name_k":"ハタガヤ","name_h":"はたがや","name_e":"hatagaya"},{"code":"671","name":"池袋東口","name_k":"イケブクロヒガシグチ","name_h":"いけぶくろひがしぐち","name_e":"ikebukurohigashiguchi"},{"code":"672","name":"ときわ台","name_k":"トキワダイ","name_h":"ときわだい","name_e":"tokiwadai"},{"code":"673","name":"王子","name_k":"オウジ","name_h":"おうじ","name_e":"ouji"},{"code":"674","name":"高松","name_k":"タカマツ","name_h":"たかまつ","name_e":"takamatsu"},{"code":"676","name":"成増","name_k":"ナリマス","name_h":"なります","name_e":"narimasu"},{"code":"677","name":"目白","name_k":"メジロ","name_h":"めじろ","name_e":"mejiro"},{"code":"678","name":"昭島","name_k":"アキシマ","name_h":"あきしま","name_e":"akishima"},{"code":"679","name":"浜松町","name_k":"ハママツチヨウ","name_h":"はままつちよう","name_e":"hamamatsuchiyou"},{"code":"681","name":"国領","name_k":"コクリヨウ","name_h":"こくりよう","name_e":"kokuriyou"},{"code":"685","name":"永山","name_k":"ナガヤマ","name_h":"ながやま","name_e":"nagayama"},{"code":"688","name":"多摩","name_k":"タマ","name_h":"たま","name_e":"tama"},{"code":"689","name":"北須磨","name_k":"キタスマ","name_h":"きたすま","name_e":"kitasuma"},{"code":"691","name":"綾瀬","name_k":"アヤセ","name_h":"あやせ","name_e":"ayase"},{"code":"693","name":"巣鴨","name_k":"スガモ","name_h":"すがも","name_e":"sugamo"},{"code":"694","name":"目黒","name_k":"メグロ","name_h":"めぐろ","name_e":"meguro"},{"code":"695","name":"日本橋","name_k":"ニホンバシ","name_h":"にほんばし","name_e":"nihonbashi"},{"code":"696","name":"三井物産ビル","name_k":"ミツイブツサンビル","name_h":"みついぶつさんびる","name_e":"mitsuibutsusanbiru"},{"code":"697","name":"福生","name_k":"フツサ","name_h":"ふつさ","name_e":"futsusa"},{"code":"698","name":"板橋中台出張所","name_k":"イタバシナカダイ","name_h":"いたばしなかだい","name_e":"itabashinakadai"},{"code":"700","name":"市川","name_k":"イチカワ","name_h":"いちかわ","name_e":"ichikawa"},{"code":"701","name":"福岡","name_k":"フクオカ","name_h":"ふくおか","name_e":"fukuoka"},{"code":"702","name":"ＡＴＭサービス西日本第一","name_k":"エ-テイ-エムニシイチ","name_h":"え-てい-えむにしいち","name_e":"e-tei-emunishiichi"},{"code":"703","name":"岡崎","name_k":"オカザキ","name_h":"おかざき","name_e":"okazaki"},{"code":"704","name":"北九州","name_k":"キタキユウシユウ","name_h":"きたきゆうしゆう","name_e":"kitakiyuushiyuu"},{"code":"705","name":"藤が丘","name_k":"フジガオカ","name_h":"ふじがおか","name_e":"fujigaoka"},{"code":"706","name":"池下","name_k":"イケシタ","name_h":"いけした","name_e":"ikeshita"},{"code":"708","name":"大牟田","name_k":"オオムタ","name_h":"おおむた","name_e":"oomuta"},{"code":"709","name":"ＡＴＭサービス西日本第二","name_k":"エ-テイ-エムニシニ","name_h":"え-てい-えむにしに","name_e":"e-tei-emunishini"},{"code":"710","name":"大阪中央","name_k":"オオサカチユウオウ","name_h":"おおさかちゆうおう","name_e":"oosakachiyuuou"},{"code":"711","name":"下関","name_k":"シモノセキ","name_h":"しものせき","name_e":"shimonoseki"},{"code":"712","name":"一社","name_k":"イツシヤ","name_h":"いつしや","name_e":"itsushiya"},{"code":"717","name":"天神町","name_k":"テンジンチヨウ","name_h":"てんじんちよう","name_e":"tenjinchiyou"},{"code":"718","name":"久留米","name_k":"クルメ","name_h":"くるめ","name_e":"kurume"},{"code":"719","name":"佐賀","name_k":"サガ","name_h":"さが","name_e":"saga"},{"code":"720","name":"熊本","name_k":"クマモト","name_h":"くまもと","name_e":"kumamoto"},{"code":"721","name":"大分","name_k":"オオイタ","name_h":"おおいた","name_e":"ooita"},{"code":"723","name":"ＡＴＭサービス西日本第三","name_k":"エ-テイ-エムニシサン","name_h":"え-てい-えむにしさん","name_e":"e-tei-emunishisan"},{"code":"725","name":"ＡＴＭサービス西日本第四","name_k":"エ-テイ-エムニシヨン","name_h":"え-てい-えむにしよん","name_e":"e-tei-emunishiyon"},{"code":"728","name":"関目","name_k":"セキメ","name_h":"せきめ","name_e":"sekime"},{"code":"729","name":"ＡＴＭサービス西日本第五","name_k":"エ-テイ-エムニシゴ","name_h":"え-てい-えむにしご","name_e":"e-tei-emunishigo"},{"code":"730","name":"東海","name_k":"トウカイ","name_h":"とうかい","name_e":"toukai"},{"code":"731","name":"九州","name_k":"キユウシユウ","name_h":"きゆうしゆう","name_e":"kiyuushiyuu"},{"code":"733","name":"八事","name_k":"ヤゴト","name_h":"やごと","name_e":"yagoto"},{"code":"734","name":"天白植田","name_k":"テンパクウエダ","name_h":"てんぱくうえだ","name_e":"tenpakuueda"},{"code":"735","name":"宝塚中山出張所","name_k":"タカラヅカナカヤマ","name_h":"たからづかなかやま","name_e":"takaradukanakayama"},{"code":"736","name":"御器所","name_k":"ゴキソ","name_h":"ごきそ","name_e":"gokiso"},{"code":"737","name":"野並","name_k":"ノナミ","name_h":"のなみ","name_e":"nonami"},{"code":"738","name":"赤池","name_k":"アカイケ","name_h":"あかいけ","name_e":"akaike"},{"code":"739","name":"大崎出張所","name_k":"オオサキ","name_h":"おおさき","name_e":"oosaki"},{"code":"740","name":"松山","name_k":"マツヤマ","name_h":"まつやま","name_e":"matsuyama"},{"code":"742","name":"立川","name_k":"タチカワ","name_h":"たちかわ","name_e":"tachikawa"},{"code":"747","name":"東戸塚","name_k":"ヒガシトツカ","name_h":"ひがしとつか","name_e":"higashitotsuka"},{"code":"748","name":"いりなか","name_k":"イリナカ","name_h":"いりなか","name_e":"irinaka"},{"code":"749","name":"金山","name_k":"カナヤマ","name_h":"かなやま","name_e":"kanayama"},{"code":"750","name":"コスモス","name_k":"コスモス","name_h":"こすもす","name_e":"kosumosu"},{"code":"751","name":"吹田","name_k":"スイタ","name_h":"すいた","name_e":"suita"},{"code":"755","name":"川崎","name_k":"カワサキ","name_h":"かわさき","name_e":"kawasaki"},{"code":"756","name":"ＡＴＭサービス西日本第六","name_k":"エ-テイ-エムニシロク","name_h":"え-てい-えむにしろく","name_e":"e-tei-emunishiroku"},{"code":"757","name":"香里","name_k":"コウリ","name_h":"こうり","name_e":"kouri"},{"code":"758","name":"四条畷","name_k":"シジヨウナワテ","name_h":"しじようなわて","name_e":"shijiyounawate"},{"code":"759","name":"阪急曽根","name_k":"ハンキユウソネ","name_h":"はんきゆうそね","name_e":"hankiyuusone"},{"code":"760","name":"すずらん","name_k":"スズラン","name_h":"すずらん","name_e":"suzuran"},{"code":"761","name":"しらゆり","name_k":"シラユリ","name_h":"しらゆり","name_e":"shirayuri"},{"code":"762","name":"ひなぎく","name_k":"ヒナギク","name_h":"ひなぎく","name_e":"hinagiku"},{"code":"763","name":"中央","name_k":"チユウオウ","name_h":"ちゆうおう","name_e":"chiyuuou"},{"code":"767","name":"ＡＴＭサービス西日本第七","name_k":"エ-テイ-エムニシナナ","name_h":"え-てい-えむにしなな","name_e":"e-tei-emunishinana"},{"code":"770","name":"ＡＴＭサービス西日本第八","name_k":"エ-テイ-エムニシハチ","name_h":"え-てい-えむにしはち","name_e":"e-tei-emunishihachi"},{"code":"772","name":"大和王寺","name_k":"ヤマトオウジ","name_h":"やまとおうじ","name_e":"yamatoouji"},{"code":"773","name":"生駒","name_k":"イコマ","name_h":"いこま","name_e":"ikoma"},{"code":"775","name":"田町相続オフィス出張所","name_k":"タマチソウゾクオフイス","name_h":"たまちそうぞくおふいす","name_e":"tamachisouzokuofuisu"},{"code":"776","name":"ドリーム出張所","name_k":"ドリ-ム","name_h":"どり-む","name_e":"dori-mu"},{"code":"779","name":"上野","name_k":"ウエノ","name_h":"うえの","name_e":"ueno"},{"code":"781","name":"茅ヶ崎","name_k":"チガサキ","name_h":"ちがさき","name_e":"chigasaki"},{"code":"785","name":"大森","name_k":"オオモリ","name_h":"おおもり","name_e":"oomori"},{"code":"788","name":"世田谷","name_k":"セタガヤ","name_h":"せたがや","name_e":"setagaya"},{"code":"791","name":"戸塚","name_k":"トツカ","name_h":"とつか","name_e":"totsuka"},{"code":"792","name":"阿佐ヶ谷","name_k":"アサガヤ","name_h":"あさがや","name_e":"asagaya"},{"code":"793","name":"宮崎台","name_k":"ミヤザキダイ","name_h":"みやざきだい","name_e":"miyazakidai"},{"code":"797","name":"志村","name_k":"シムラ","name_h":"しむら","name_e":"shimura"},{"code":"804","name":"深川","name_k":"フカガワ","name_h":"ふかがわ","name_e":"fukagawa"},{"code":"808","name":"六郷","name_k":"ロクゴウ","name_h":"ろくごう","name_e":"rokugou"},{"code":"810","name":"下丸子","name_k":"シモマルコ","name_h":"しもまるこ","name_e":"shimomaruko"},{"code":"813","name":"小石川","name_k":"コイシカワ","name_h":"こいしかわ","name_e":"koishikawa"},{"code":"814","name":"中野坂上","name_k":"ナカノサカウエ","name_h":"なかのさかうえ","name_e":"nakanosakaue"},{"code":"821","name":"江戸川","name_k":"エドガワ","name_h":"えどがわ","name_e":"edogawa"},{"code":"823","name":"葛西","name_k":"カサイ","name_h":"かさい","name_e":"kasai"},{"code":"825","name":"赤坂","name_k":"アカサカ","name_h":"あかさか","name_e":"akasaka"},{"code":"828","name":"品川","name_k":"シナガワ","name_h":"しながわ","name_e":"shinagawa"},{"code":"831","name":"二子玉川","name_k":"フタコタマガワ","name_h":"ふたこたまがわ","name_e":"futakotamagawa"},{"code":"832","name":"つつじヶ丘","name_k":"ツツジガオカ","name_h":"つつじがおか","name_e":"tsutsujigaoka"},{"code":"835","name":"下北沢","name_k":"シモキタザワ","name_h":"しもきたざわ","name_e":"shimokitazawa"},{"code":"836","name":"国分寺","name_k":"コクブンジ","name_h":"こくぶんじ","name_e":"kokubunji"},{"code":"839","name":"五反野","name_k":"ゴタンノ","name_h":"ごたんの","name_e":"gotan'no"},{"code":"841","name":"生田","name_k":"イクタ","name_h":"いくた","name_e":"ikuta"},{"code":"843","name":"八王子","name_k":"ハチオウジ","name_h":"はちおうじ","name_e":"hachiouji"},{"code":"844","name":"新松戸出張所","name_k":"シンマツド","name_h":"しんまつど","name_e":"shinmatsudo"},{"code":"845","name":"吉祥寺","name_k":"キチジヨウジ","name_h":"きちじようじ","name_e":"kichijiyouji"},{"code":"847","name":"町田","name_k":"マチダ","name_h":"まちだ","name_e":"machida"},{"code":"848","name":"小金井","name_k":"コガネイ","name_h":"こがねい","name_e":"koganei"},{"code":"849","name":"清瀬","name_k":"キヨセ","name_h":"きよせ","name_e":"kiyose"},{"code":"851","name":"田無","name_k":"タナシ","name_h":"たなし","name_e":"tanashi"},{"code":"852","name":"東大和","name_k":"ヒガシヤマト","name_h":"ひがしやまと","name_e":"higashiyamato"},{"code":"855","name":"新所沢","name_k":"シントコロザワ","name_h":"しんところざわ","name_e":"shintokorozawa"},{"code":"856","name":"新検見川","name_k":"シンケミガワ","name_h":"しんけみがわ","name_e":"shinkemigawa"},{"code":"858","name":"相模大野","name_k":"サガミオオノ","name_h":"さがみおおの","name_e":"sagamioono"},{"code":"862","name":"小田原","name_k":"オダワラ","name_h":"おだわら","name_e":"odawara"},{"code":"867","name":"中山","name_k":"ナカヤマ","name_h":"なかやま","name_e":"nakayama"},{"code":"868","name":"伊勢原","name_k":"イセハラ","name_h":"いせはら","name_e":"isehara"},{"code":"870","name":"ジャスミン","name_k":"ジヤスミン","name_h":"じやすみん","name_e":"jiyasumin"},{"code":"873","name":"大船","name_k":"オオフナ","name_h":"おおふな","name_e":"oofuna"},{"code":"879","name":"ツバキ","name_k":"ツバキ","name_h":"つばき","name_e":"tsubaki"},{"code":"884","name":"ぼたん","name_k":"ボタン","name_h":"ぼたん","name_e":"botan"},{"code":"888","name":"飯田橋","name_k":"イイダバシ","name_h":"いいだばし","name_e":"iidabashi"},{"code":"890","name":"元住吉","name_k":"モトスミヨシ","name_h":"もとすみよし","name_e":"motosumiyoshi"},{"code":"891","name":"津田沼駅前","name_k":"ツダヌマエキマエ","name_h":"つだぬまえきまえ","name_e":"tsudanumaekimae"},{"code":"893","name":"船橋北口","name_k":"フナバシキタグチ","name_h":"ふなばしきたぐち","name_e":"funabashikitaguchi"},{"code":"894","name":"相模原","name_k":"サガミハラ","name_h":"さがみはら","name_e":"sagamihara"},{"code":"904","name":"千川","name_k":"センカワ","name_h":"せんかわ","name_e":"senkawa"},{"code":"905","name":"鎌ヶ谷","name_k":"カマガヤ","name_h":"かまがや","name_e":"kamagaya"},{"code":"906","name":"高尾","name_k":"タカオ","name_h":"たかお","name_e":"takao"},{"code":"907","name":"御岳山出張所","name_k":"オンタケサン","name_h":"おんたけさん","name_e":"ontakesan"},{"code":"909","name":"多摩センター","name_k":"タマセンタ-","name_h":"たませんた-","name_e":"tamasenta-"},{"code":"910","name":"水戸","name_k":"ミト","name_h":"みと","name_e":"mito"},{"code":"916","name":"調布駅前","name_k":"チヨウフエキマエ","name_h":"ちようふえきまえ","name_e":"chiyoufuekimae"},{"code":"921","name":"笹塚","name_k":"ササヅカ","name_h":"ささづか","name_e":"sasaduka"},{"code":"924","name":"梅田相続オフィス出張所","name_k":"ウメダソウゾクオフイス","name_h":"うめだそうぞくおふいす","name_e":"umedasouzokuofuisu"},{"code":"925","name":"東日本","name_k":"ヒガシニホン","name_h":"ひがしにほん","name_e":"higashinihon"},{"code":"926","name":"首都圏","name_k":"シユトケン","name_h":"しゆとけん","name_e":"shiyutoken"},{"code":"928","name":"ＳＭＢＣ日興証券","name_k":"エスエムビ-シ-ニツコウ","name_h":"えすえむび-し-につこう","name_e":"esuemubi-shi-nitsukou"},{"code":"929","name":"武蔵小杉","name_k":"ムサシコスギ","name_h":"むさしこすぎ","name_e":"musashikosugi"},{"code":"930","name":"日吉","name_k":"ヒヨシ","name_h":"ひよし","name_e":"hiyoshi"},{"code":"931","name":"東京第一","name_k":"トウキヨウダイイチ","name_h":"とうきようだいいち","name_e":"toukiyoudaiichi"},{"code":"932","name":"湘南台","name_k":"シヨウナンダイ","name_h":"しようなんだい","name_e":"shiyounandai"},{"code":"933","name":"鎌倉","name_k":"カマクラ","name_h":"かまくら","name_e":"kamakura"},{"code":"935","name":"ライラック","name_k":"ライラツク","name_h":"らいらつく","name_e":"rairatsuku"},{"code":"936","name":"守谷","name_k":"モリヤ","name_h":"もりや","name_e":"moriya"},{"code":"939","name":"れんげ","name_k":"レンゲ","name_h":"れんげ","name_e":"renge"},{"code":"940","name":"若葉台","name_k":"ワカバダイ","name_h":"わかばだい","name_e":"wakabadai"},{"code":"941","name":"大阪第一","name_k":"オオサカダイイチ","name_h":"おおさかだいいち","name_e":"oosakadaiichi"},{"code":"943","name":"ホオズキ","name_k":"ホオズキ","name_h":"ほおずき","name_e":"hoozuki"},{"code":"945","name":"和泉中央","name_k":"イズミチユウオウ","name_h":"いずみちゆうおう","name_e":"izumichiyuuou"},{"code":"946","name":"クロッカス","name_k":"クロツカス","name_h":"くろつかす","name_e":"kurotsukasu"},{"code":"948","name":"ベイサイド","name_k":"ベイサイド","name_h":"べいさいど","name_e":"beisaido"},{"code":"949","name":"少路","name_k":"シヨウジ","name_h":"しようじ","name_e":"shiyouji"},{"code":"950","name":"東京第二","name_k":"トウキヨウダイニ","name_h":"とうきようだいに","name_e":"toukiyoudaini"},{"code":"952","name":"センター南","name_k":"センタ-ミナミ","name_h":"せんた-みなみ","name_e":"senta-minami"},{"code":"953","name":"ドットコム","name_k":"ドツトコム","name_h":"どつとこむ","name_e":"dotsutokomu"},{"code":"954","name":"あじさい","name_k":"アジサイ","name_h":"あじさい","name_e":"ajisai"},{"code":"955","name":"福山","name_k":"フクヤマ","name_h":"ふくやま","name_e":"fukuyama"},{"code":"956","name":"すみれ","name_k":"スミレ","name_h":"すみれ","name_e":"sumire"},{"code":"958","name":"ひまわり","name_k":"ヒマワリ","name_h":"ひまわり","name_e":"himawari"},{"code":"959","name":"武蔵浦和","name_k":"ムサシウラワ","name_h":"むさしうらわ","name_e":"musashiurawa"},{"code":"960","name":"関東第二","name_k":"カントウダイニ","name_h":"かんとうだいに","name_e":"kantoudaini"},{"code":"961","name":"光明池","name_k":"コウミヨウイケ","name_h":"こうみよういけ","name_e":"koumiyouike"},{"code":"962","name":"関東第三","name_k":"カントウダイサン","name_h":"かんとうだいさん","name_e":"kantoudaisan"},{"code":"963","name":"あさがお","name_k":"アサガオ","name_h":"あさがお","name_e":"asagao"},{"code":"964","name":"カトレア","name_k":"カトレア","name_h":"かとれあ","name_e":"katorea"},{"code":"965","name":"八千代緑が丘","name_k":"ヤチヨミドリガオカ","name_h":"やちよみどりがおか","name_e":"yachiyomidorigaoka"},{"code":"966","name":"松井山手出張所","name_k":"マツイヤマテ","name_h":"まついやまて","name_e":"matsuiyamate"},{"code":"967","name":"ふじみ野","name_k":"フジミノ","name_h":"ふじみの","name_e":"fujimino"},{"code":"968","name":"関東第一","name_k":"カントウダイイチ","name_h":"かんとうだいいち","name_e":"kantoudaiichi"},{"code":"969","name":"アオイ","name_k":"アオイ","name_h":"あおい","name_e":"aoi"},{"code":"970","name":"りんどう","name_k":"リンドウ","name_h":"りんどう","name_e":"rindou"},{"code":"971","name":"なでしこ","name_k":"ナデシコ","name_h":"なでしこ","name_e":"nadeshiko"},{"code":"972","name":"日興","name_k":"ニツコウ","name_h":"につこう","name_e":"nitsukou"},{"code":"974","name":"近畿第一","name_k":"キンキダイイチ","name_h":"きんきだいいち","name_e":"kinkidaiichi"},{"code":"976","name":"ラベンダー","name_k":"ラベンダ-","name_h":"らべんだ-","name_e":"rabenda-"},{"code":"977","name":"すいせん","name_k":"スイセン","name_h":"すいせん","name_e":"suisen"},{"code":"978","name":"たんぽぽ","name_k":"タンポポ","name_h":"たんぽぽ","name_e":"tanpopo"},{"code":"979","name":"はまゆう","name_k":"ハマユウ","name_h":"はまゆう","name_e":"hamayuu"},{"code":"980","name":"大阪第二","name_k":"オオサカダイニ","name_h":"おおさかだいに","name_e":"oosakadaini"},{"code":"982","name":"西日本","name_k":"ニシニホン","name_h":"にしにほん","name_e":"nishinihon"},{"code":"984","name":"やなぎ","name_k":"ヤナギ","name_h":"やなぎ","name_e":"yanagi"},{"code":"985","name":"近畿第二","name_k":"キンキダイニ","name_h":"きんきだいに","name_e":"kinkidaini"},{"code":"986","name":"ヒルトップ","name_k":"ヒルトツプ","name_h":"ひるとつぷ","name_e":"hirutotsupu"},{"code":"987","name":"豊洲出張所","name_k":"トヨス","name_h":"とよす","name_e":"toyosu"},{"code":"988","name":"ウェブサイト","name_k":"ウエブサイト","name_h":"うえぶさいと","name_e":"uebusaito"},{"code":"989","name":"海老名","name_k":"エビナ","name_h":"えびな","name_e":"ebina"}]