[{"code":"111","name":"本店営業部","name_k":"ホンテン","name_h":"ほんてん","name_e":"honten"},{"code":"112","name":"秋田市役所","name_k":"アキタシヤクシヨ","name_h":"あきたしやくしよ","name_e":"akitashiyakushiyo"},{"code":"113","name":"大町","name_k":"オオマチ","name_h":"おおまち","name_e":"oomachi"},{"code":"115","name":"馬口労町","name_k":"バクロウマチ","name_h":"ばくろうまち","name_e":"bakuroumachi"},{"code":"116","name":"県庁","name_k":"ケンチヨウ","name_h":"けんちよう","name_e":"kenchiyou"},{"code":"117","name":"新屋","name_k":"アラヤ","name_h":"あらや","name_e":"araya"},{"code":"118","name":"泉","name_k":"イズミ","name_h":"いずみ","name_e":"izumi"},{"code":"121","name":"泉中央","name_k":"イズミチユウオウ","name_h":"いずみちゆうおう","name_e":"izumichiyuuou"},{"code":"122","name":"寺内","name_k":"テラウチ","name_h":"てらうち","name_e":"terauchi"},{"code":"124","name":"八橋","name_k":"ヤバセ","name_h":"やばせ","name_e":"yabase"},{"code":"125","name":"割山","name_k":"ワリヤマ","name_h":"わりやま","name_e":"wariyama"},{"code":"128","name":"山王","name_k":"サンノウ","name_h":"さんのう","name_e":"san'nou"},{"code":"131","name":"南通り","name_k":"ミナミドオリ","name_h":"みなみどおり","name_e":"minamidoori"},{"code":"132","name":"秋田駅前","name_k":"アキタエキマエ","name_h":"あきたえきまえ","name_e":"akitaekimae"},{"code":"133","name":"手形","name_k":"テガタ","name_h":"てがた","name_e":"tegata"},{"code":"134","name":"牛島","name_k":"ウシジマ","name_h":"うしじま","name_e":"ushijima"},{"code":"135","name":"卸町","name_k":"オロシマチ","name_h":"おろしまち","name_e":"oroshimachi"},{"code":"137","name":"広面","name_k":"ヒロオモテ","name_h":"ひろおもて","name_e":"hiroomote"},{"code":"142","name":"御野場","name_k":"オノバ","name_h":"おのば","name_e":"onoba"},{"code":"143","name":"楢山","name_k":"ナラヤマ","name_h":"ならやま","name_e":"narayama"},{"code":"145","name":"手形北","name_k":"テガタキタ","name_h":"てがたきた","name_e":"tegatakita"},{"code":"146","name":"桜","name_k":"サクラ","name_h":"さくら","name_e":"sakura"},{"code":"147","name":"秋田東中央","name_k":"アキタヒガシチユウオウ","name_h":"あきたひがしちゆうおう","name_e":"akitahigashichiyuuou"},{"code":"148","name":"御所野ニュータウン","name_k":"ゴシヨノニユ-タウン","name_h":"ごしよのにゆ-たうん","name_e":"goshiyononiyu-taun"},{"code":"151","name":"土崎","name_k":"ツチザキ","name_h":"つちざき","name_e":"tsuchizaki"},{"code":"152","name":"将軍野","name_k":"シヨウグンノ","name_h":"しようぐんの","name_e":"shiyougun'no"},{"code":"154","name":"港北","name_k":"コウホク","name_h":"こうほく","name_e":"kouhoku"},{"code":"156","name":"外旭川","name_k":"ソトアサヒカワ","name_h":"そとあさひかわ","name_e":"sotoasahikawa"},{"code":"161","name":"追分","name_k":"オイワケ","name_h":"おいわけ","name_e":"oiwake"},{"code":"171","name":"男鹿","name_k":"オガ","name_h":"おが","name_e":"oga"},{"code":"172","name":"船越","name_k":"フナコシ","name_h":"ふなこし","name_e":"funakoshi"},{"code":"173","name":"北浦出張所","name_k":"キタウラ","name_h":"きたうら","name_e":"kitaura"},{"code":"174","name":"天王","name_k":"テンノウ","name_h":"てんのう","name_e":"ten'nou"},{"code":"181","name":"大久保","name_k":"オオクボ","name_h":"おおくぼ","name_e":"ookubo"},{"code":"182","name":"五城目","name_k":"ゴジヨウメ","name_h":"ごじようめ","name_e":"gojiyoume"},{"code":"183","name":"大潟","name_k":"オオガタ","name_h":"おおがた","name_e":"oogata"},{"code":"211","name":"能代","name_k":"ノシロ","name_h":"のしろ","name_e":"noshiro"},{"code":"213","name":"八森","name_k":"ハチモリ","name_h":"はちもり","name_e":"hachimori"},{"code":"214","name":"能代南","name_k":"ノシロミナミ","name_h":"のしろみなみ","name_e":"noshirominami"},{"code":"221","name":"鹿渡","name_k":"カド","name_h":"かど","name_e":"kado"},{"code":"222","name":"二ツ井","name_k":"フタツイ","name_h":"ふたつい","name_e":"futatsui"},{"code":"223","name":"藤里","name_k":"フジサト","name_h":"ふじさと","name_e":"fujisato"},{"code":"231","name":"大館","name_k":"オオダテ","name_h":"おおだて","name_e":"oodate"},{"code":"232","name":"大館駅前","name_k":"オオダテエキマエ","name_h":"おおだてえきまえ","name_e":"oodateekimae"},{"code":"233","name":"大館西","name_k":"オオダテニシ","name_h":"おおだてにし","name_e":"oodatenishi"},{"code":"241","name":"鷹巣","name_k":"タカノス","name_h":"たかのす","name_e":"takanosu"},{"code":"242","name":"阿仁合","name_k":"アニアイ","name_h":"あにあい","name_e":"aniai"},{"code":"243","name":"田代","name_k":"タシロ","name_h":"たしろ","name_e":"tashiro"},{"code":"244","name":"比内","name_k":"ヒナイ","name_h":"ひない","name_e":"hinai"},{"code":"251","name":"小坂","name_k":"コサカ","name_h":"こさか","name_e":"kosaka"},{"code":"252","name":"毛馬内","name_k":"ケマナイ","name_h":"けまない","name_e":"kemanai"},{"code":"253","name":"大湯","name_k":"オオユ","name_h":"おおゆ","name_e":"ooyu"},{"code":"254","name":"花輪","name_k":"ハナワ","name_h":"はなわ","name_e":"hanawa"},{"code":"261","name":"河辺","name_k":"カワベ","name_h":"かわべ","name_e":"kawabe"},{"code":"262","name":"雄和","name_k":"ユウワ","name_h":"ゆうわ","name_e":"yuuwa"},{"code":"311","name":"大曲","name_k":"オオマガリ","name_h":"おおまがり","name_e":"oomagari"},{"code":"312","name":"大曲駅前","name_k":"オオマガリエキマエ","name_h":"おおまがりえきまえ","name_e":"oomagariekimae"},{"code":"313","name":"角間川","name_k":"カクマガワ","name_h":"かくまがわ","name_e":"kakumagawa"},{"code":"321","name":"刈和野","name_k":"カリワノ","name_h":"かりわの","name_e":"kariwano"},{"code":"322","name":"協和","name_k":"キヨウワ","name_h":"きようわ","name_e":"kiyouwa"},{"code":"323","name":"神宮寺","name_k":"ジングウジ","name_h":"じんぐうじ","name_e":"jinguuji"},{"code":"324","name":"長野","name_k":"ナガノ","name_h":"ながの","name_e":"nagano"},{"code":"325","name":"角館","name_k":"カクノダテ","name_h":"かくのだて","name_e":"kakunodate"},{"code":"326","name":"田沢湖","name_k":"タザワコ","name_h":"たざわこ","name_e":"tazawako"},{"code":"327","name":"六郷","name_k":"ロクゴウ","name_h":"ろくごう","name_e":"rokugou"},{"code":"341","name":"横手","name_k":"ヨコテ","name_h":"よこて","name_e":"yokote"},{"code":"342","name":"横手条里","name_k":"ヨコテジヨウリ","name_h":"よこてじようり","name_e":"yokotejiyouri"},{"code":"351","name":"十文字","name_k":"ジユウモンジ","name_h":"じゆうもんじ","name_e":"jiyuumonji"},{"code":"352","name":"増田","name_k":"マスダ","name_h":"ますだ","name_e":"masuda"},{"code":"353","name":"浅舞","name_k":"アサマイ","name_h":"あさまい","name_e":"asamai"},{"code":"361","name":"湯沢","name_k":"ユザワ","name_h":"ゆざわ","name_e":"yuzawa"},{"code":"362","name":"西馬音内","name_k":"ニシモナイ","name_h":"にしもない","name_e":"nishimonai"},{"code":"364","name":"稲川","name_k":"イナカワ","name_h":"いなかわ","name_e":"inakawa"},{"code":"381","name":"本荘","name_k":"ホンジヨウ","name_h":"ほんじよう","name_e":"honjiyou"},{"code":"382","name":"本荘東","name_k":"ホンジヨウヒガシ","name_h":"ほんじようひがし","name_e":"honjiyouhigashi"},{"code":"383","name":"岩城町","name_k":"イワキマチ","name_h":"いわきまち","name_e":"iwakimachi"},{"code":"391","name":"金浦","name_k":"コノウラ","name_h":"このうら","name_e":"konoura"},{"code":"392","name":"矢島","name_k":"ヤシマ","name_h":"やしま","name_e":"yashima"},{"code":"393","name":"象潟","name_k":"キサカタ","name_h":"きさかた","name_e":"kisakata"},{"code":"394","name":"仁賀保","name_k":"ニカホ","name_h":"にかほ","name_e":"nikaho"},{"code":"411","name":"札幌","name_k":"サツポロ","name_h":"さつぽろ","name_e":"satsuporo"},{"code":"412","name":"旭川","name_k":"アサヒカワ","name_h":"あさひかわ","name_e":"asahikawa"},{"code":"431","name":"八戸","name_k":"ハチノヘ","name_h":"はちのへ","name_e":"hachinohe"},{"code":"432","name":"青森","name_k":"アオモリ","name_h":"あおもり","name_e":"aomori"},{"code":"433","name":"弘前","name_k":"ヒロサキ","name_h":"ひろさき","name_e":"hirosaki"},{"code":"441","name":"盛岡","name_k":"モリオカ","name_h":"もりおか","name_e":"morioka"},{"code":"451","name":"仙台","name_k":"センダイ","name_h":"せんだい","name_e":"sendai"},{"code":"452","name":"仙台南","name_k":"センダイミナミ","name_h":"せんだいみなみ","name_e":"sendaiminami"},{"code":"453","name":"仙台泉中央","name_k":"センダイイズミチユウオウ","name_h":"せんだいいずみちゆうおう","name_e":"sendaiizumichiyuuou"},{"code":"471","name":"福島","name_k":"フクシマ","name_h":"ふくしま","name_e":"fukushima"},{"code":"472","name":"郡山","name_k":"コオリヤマ","name_h":"こおりやま","name_e":"kooriyama"},{"code":"473","name":"いわき","name_k":"イワキ","name_h":"いわき","name_e":"iwaki"},{"code":"475","name":"郡山北","name_k":"コオリヤマキタ","name_h":"こおりやまきた","name_e":"kooriyamakita"},{"code":"476","name":"郡山南","name_k":"コオリヤマミナミ","name_h":"こおりやまみなみ","name_e":"kooriyamaminami"},{"code":"481","name":"新潟","name_k":"ニイガタ","name_h":"にいがた","name_e":"niigata"},{"code":"511","name":"東京","name_k":"トウキヨウ","name_h":"とうきよう","name_e":"toukiyou"},{"code":"551","name":"あきぎんこまち","name_k":"アキギンコマチ","name_h":"あきぎんこまち","name_e":"akiginkomachi"},{"code":"933","name":"イーネットＡＴＭ","name_k":"イ-ネツトエイテイエム","name_h":"い-ねつとえいていえむ","name_e":"i-netsutoeiteiemu"},{"code":"934","name":"ローソンＡＴＭ","name_k":"ロ-ソンエイテイエム","name_h":"ろ-そんえいていえむ","name_e":"ro-son'eiteiemu"}]