[{"bank_code":"1204","code":"001","name":"本店","name_k":"ホンテン","name_h":"ほんてん","name_e":"honten"},{"bank_code":"1204","code":"002","name":"本町","name_k":"ホンチヨウ","name_h":"ほんちよう","name_e":"honchiyou"},{"bank_code":"1204","code":"003","name":"西","name_k":"ニシ","name_h":"にし","name_e":"nishi"},{"bank_code":"1204","code":"004","name":"新桐生","name_k":"シンキリユウ","name_h":"しんきりゆう","name_e":"shinkiriyuu"},{"bank_code":"1204","code":"005","name":"大間々","name_k":"オオママ","name_h":"おおまま","name_e":"oomama"},{"bank_code":"1204","code":"006","name":"太田","name_k":"オオタ","name_h":"おおた","name_e":"oota"},{"bank_code":"1204","code":"007","name":"相生","name_k":"アイオイ","name_h":"あいおい","name_e":"aioi"},{"bank_code":"1204","code":"009","name":"太田西","name_k":"オオタニシ","name_h":"おおたにし","name_e":"ootanishi"},{"bank_code":"1204","code":"010","name":"前橋","name_k":"マエバシ","name_h":"まえばし","name_e":"maebashi"},{"bank_code":"1204","code":"011","name":"広沢","name_k":"ヒロサワ","name_h":"ひろさわ","name_e":"hirosawa"},{"bank_code":"1204","code":"012","name":"笠懸","name_k":"カサカケ","name_h":"かさかけ","name_e":"kasakake"},{"bank_code":"1204","code":"013","name":"川内","name_k":"カワウチ","name_h":"かわうち","name_e":"kawauchi"},{"bank_code":"1204","code":"014","name":"東","name_k":"ヒガシ","name_h":"ひがし","name_e":"higashi"},{"bank_code":"1204","code":"015","name":"境野","name_k":"サカイノ","name_h":"さかいの","name_e":"sakaino"},{"bank_code":"1204","code":"016","name":"高林","name_k":"タカハヤシ","name_h":"たかはやし","name_e":"takahayashi"},{"bank_code":"1204","code":"017","name":"薮塚","name_k":"ヤブヅカ","name_h":"やぶづか","name_e":"yabuduka"},{"bank_code":"1204","code":"018","name":"国定","name_k":"クニサダ","name_h":"くにさだ","name_e":"kunisada"},{"bank_code":"1204","code":"019","name":"梅田","name_k":"ウメダ","name_h":"うめだ","name_e":"umeda"},{"bank_code":"1204","code":"021","name":"堀込","name_k":"ホリゴメ","name_h":"ほりごめ","name_e":"horigome"},{"bank_code":"1204","code":"022","name":"伊勢崎","name_k":"イセサキ","name_h":"いせさき","name_e":"isesaki"},{"bank_code":"1204","code":"023","name":"久宮","name_k":"クグウ","name_h":"くぐう","name_e":"kuguu"},{"bank_code":"1204","code":"024","name":"新田","name_k":"ニツタ","name_h":"につた","name_e":"nitsuta"},{"bank_code":"1204","code":"029","name":"みどり","name_k":"ミドリ","name_h":"みどり","name_e":"midori"},{"bank_code":"1204","code":"030","name":"玉村","name_k":"タマムラ","name_h":"たまむら","name_e":"tamamura"},{"bank_code":"1204","code":"031","name":"伊勢崎西","name_k":"イセサキニシ","name_h":"いせさきにし","name_e":"isesakinishi"},{"bank_code":"1204","code":"033","name":"内ヶ島","name_k":"ウチガシマ","name_h":"うちがしま","name_e":"uchigashima"},{"bank_code":"1204","code":"035","name":"韮川","name_k":"ニラガワ","name_h":"にらがわ","name_e":"niragawa"},{"bank_code":"1204","code":"036","name":"伊勢崎東","name_k":"イセサキヒガシ","name_h":"いせさきひがし","name_e":"isesakihigashi"},{"bank_code":"1204","code":"037","name":"伊勢崎南","name_k":"イセサキミナミ","name_h":"いせさきみなみ","name_e":"isesakiminami"},{"bank_code":"1204","code":"038","name":"境","name_k":"サカイ","name_h":"さかい","name_e":"sakai"},{"bank_code":"1204","code":"039","name":"大泉","name_k":"オオイズミ","name_h":"おおいずみ","name_e":"ooizumi"},{"bank_code":"1204","code":"040","name":"前橋東","name_k":"マエバシヒガシ","name_h":"まえばしひがし","name_e":"maebashihigashi"},{"bank_code":"1204","code":"041","name":"豊受","name_k":"トヨウケ","name_h":"とようけ","name_e":"toyouke"},{"bank_code":"1204","code":"043","name":"赤堀","name_k":"アカボリ","name_h":"あかぼり","name_e":"akabori"}]