[{"code":"001","name":"本店","name_k":"ホンテン","name_h":"ほんてん","name_e":"honten"},{"code":"003","name":"仲町","name_k":"ナカチヨウ","name_h":"なかちよう","name_e":"nakachiyou"},{"code":"004","name":"飯塚","name_k":"イイヅカ","name_h":"いいづか","name_e":"iiduka"},{"code":"005","name":"蕨","name_k":"ワラビ","name_h":"わらび","name_e":"warabi"},{"code":"006","name":"戸田","name_k":"トダ","name_h":"とだ","name_e":"toda"},{"code":"007","name":"志木","name_k":"シキ","name_h":"しき","name_e":"shiki"},{"code":"008","name":"和光","name_k":"ワコウ","name_h":"わこう","name_e":"wakou"},{"code":"009","name":"本町東","name_k":"ホンチヨウヒガシ","name_h":"ほんちようひがし","name_e":"honchiyouhigashi"},{"code":"010","name":"蒲生","name_k":"ガモウ","name_h":"がもう","name_e":"gamou"},{"code":"011","name":"芝","name_k":"シバ","name_h":"しば","name_e":"shiba"},{"code":"012","name":"大宮","name_k":"オオミヤ","name_h":"おおみや","name_e":"oomiya"},{"code":"013","name":"一ノ割","name_k":"イチノワリ","name_h":"いちのわり","name_e":"ichinowari"},{"code":"014","name":"与野","name_k":"ヨノ","name_h":"よの","name_e":"yono"},{"code":"015","name":"柳崎","name_k":"ヤナギサキ","name_h":"やなぎさき","name_e":"yanagisaki"},{"code":"016","name":"北浦和","name_k":"キタウラワ","name_h":"きたうらわ","name_e":"kitaurawa"},{"code":"017","name":"鳩ヶ谷","name_k":"ハトガヤ","name_h":"はとがや","name_e":"hatogaya"},{"code":"018","name":"宗岡","name_k":"ムネオカ","name_h":"むねおか","name_e":"muneoka"},{"code":"019","name":"木曽呂","name_k":"キゾロ","name_h":"きぞろ","name_e":"kizoro"},{"code":"020","name":"大和田","name_k":"オオワダ","name_h":"おおわだ","name_e":"oowada"},{"code":"021","name":"武蔵浦和","name_k":"ムサシウラワ","name_h":"むさしうらわ","name_e":"musashiurawa"},{"code":"022","name":"川口中央","name_k":"カワグチチユウオウ","name_h":"かわぐちちゆうおう","name_e":"kawaguchichiyuuou"},{"code":"023","name":"浦和中尾","name_k":"ウラワナカオ","name_h":"うらわなかお","name_e":"urawanakao"},{"code":"024","name":"東川口","name_k":"ヒガシカワグチ","name_h":"ひがしかわぐち","name_e":"higashikawaguchi"},{"code":"025","name":"赤井","name_k":"アカイ","name_h":"あかい","name_e":"akai"},{"code":"027","name":"戸田北","name_k":"トダキタ","name_h":"とだきた","name_e":"todakita"},{"code":"028","name":"蒲生西口","name_k":"ガモウニシグチ","name_h":"がもうにしぐち","name_e":"gamounishiguchi"},{"code":"029","name":"志木北","name_k":"シキキタ","name_h":"しききた","name_e":"shikikita"},{"code":"031","name":"東大宮","name_k":"ヒガシオオミヤ","name_h":"ひがしおおみや","name_e":"higashioomiya"},{"code":"032","name":"上尾","name_k":"アゲオ","name_h":"あげお","name_e":"ageo"},{"code":"033","name":"東本郷","name_k":"ヒガシホンゴウ","name_h":"ひがしほんごう","name_e":"higashihongou"},{"code":"034","name":"みずほ台","name_k":"ミズホダイ","name_h":"みずほだい","name_e":"mizuhodai"},{"code":"035","name":"岩槻","name_k":"イワツキ","name_h":"いわつき","name_e":"iwatsuki"},{"code":"036","name":"南越谷","name_k":"ミナミコシガヤ","name_h":"みなみこしがや","name_e":"minamikoshigaya"},{"code":"037","name":"土呂","name_k":"トロ","name_h":"とろ","name_e":"toro"},{"code":"038","name":"浦和道場","name_k":"ウラワドウジヨウ","name_h":"うらわどうじよう","name_e":"urawadoujiyou"},{"code":"039","name":"桶川","name_k":"オケガワ","name_h":"おけがわ","name_e":"okegawa"},{"code":"040","name":"春日部","name_k":"カスカベ","name_h":"かすかべ","name_e":"kasukabe"},{"code":"041","name":"東浦和駅前","name_k":"ヒガシウラワエキマエ","name_h":"ひがしうらわえきまえ","name_e":"higashiurawaekimae"},{"code":"042","name":"宮代","name_k":"ミヤシロ","name_h":"みやしろ","name_e":"miyashiro"},{"code":"043","name":"鷲宮","name_k":"ワシノミヤ","name_h":"わしのみや","name_e":"washinomiya"},{"code":"044","name":"ふじみ野","name_k":"フジミノ","name_h":"ふじみの","name_e":"fujimino"},{"code":"045","name":"栗橋","name_k":"クリハシ","name_h":"くりはし","name_e":"kurihashi"},{"code":"046","name":"久喜","name_k":"クキ","name_h":"くき","name_e":"kuki"},{"code":"047","name":"せんげん台","name_k":"センゲンダイ","name_h":"せんげんだい","name_e":"sengendai"},{"code":"048","name":"鴻巣","name_k":"コウノス","name_h":"こうのす","name_e":"kounosu"}]