[{"code":"001","name":"本店","name_k":"ホンテン","name_h":"ほんてん","name_e":"honten"},{"code":"002","name":"宗像","name_k":"ムナカタ","name_h":"むなかた","name_e":"munakata"},{"code":"003","name":"赤間","name_k":"アカマ","name_h":"あかま","name_e":"akama"},{"code":"007","name":"福間","name_k":"フクマ","name_h":"ふくま","name_e":"fukuma"},{"code":"010","name":"古賀","name_k":"コガ","name_h":"こが","name_e":"koga"},{"code":"011","name":"清川","name_k":"キヨカワ","name_h":"きよかわ","name_e":"kiyokawa"},{"code":"015","name":"志免","name_k":"シメ","name_h":"しめ","name_e":"shime"},{"code":"016","name":"亀山","name_k":"カメヤマ","name_h":"かめやま","name_e":"kameyama"},{"code":"017","name":"宇美","name_k":"ウミ","name_h":"うみ","name_e":"umi"},{"code":"018","name":"飯塚","name_k":"イイヅカ","name_h":"いいづか","name_e":"iiduka"},{"code":"020","name":"碓井","name_k":"ウスイ","name_h":"うすい","name_e":"usui"},{"code":"021","name":"大橋","name_k":"オオハシ","name_h":"おおはし","name_e":"oohashi"},{"code":"022","name":"高宮","name_k":"タカミヤ","name_h":"たかみや","name_e":"takamiya"},{"code":"024","name":"春日","name_k":"カスガ","name_h":"かすが","name_e":"kasuga"},{"code":"027","name":"青果市場","name_k":"セイカイチバ","name_h":"せいかいちば","name_e":"seikaichiba"},{"code":"032","name":"前原","name_k":"マエバル","name_h":"まえばる","name_e":"maebaru"},{"code":"033","name":"周船寺","name_k":"スセンジ","name_h":"すせんじ","name_e":"susenji"},{"code":"034","name":"加布里","name_k":"カフリ","name_h":"かふり","name_e":"kafuri"},{"code":"036","name":"今宿","name_k":"イマジユク","name_h":"いまじゆく","name_e":"imajiyuku"},{"code":"037","name":"博多駅東","name_k":"ハカタエキヒガシ","name_h":"はかたえきひがし","name_e":"hakataekihigashi"}]