[{"bank_code":"6345","code":"002","name":"静浦","name_k":"シズウラ","name_h":"しずうら","name_e":"shizuura"},{"bank_code":"6345","code":"003","name":"大平","name_k":"オオヒラ","name_h":"おおひら","name_e":"oohira"},{"bank_code":"6345","code":"004","name":"大岡","name_k":"オオオカ","name_h":"おおおか","name_e":"oooka"},{"bank_code":"6345","code":"005","name":"金岡","name_k":"カナオカ","name_h":"かなおか","name_e":"kanaoka"},{"bank_code":"6345","code":"006","name":"愛鷹","name_k":"アシタカ","name_h":"あしたか","name_e":"ashitaka"},{"bank_code":"6345","code":"007","name":"浮島","name_k":"ウキシマ","name_h":"うきしま","name_e":"ukishima"},{"bank_code":"6345","code":"008","name":"原","name_k":"ハラ","name_h":"はら","name_e":"hara"},{"bank_code":"6345","code":"012","name":"北小林","name_k":"キタコバヤシ","name_h":"きたこばやし","name_e":"kitakobayashi"},{"bank_code":"6345","code":"013","name":"東椎路","name_k":"ヒガシシイジ","name_h":"ひがししいじ","name_e":"higashishiiji"},{"bank_code":"6345","code":"014","name":"光長寺前","name_k":"コウチヨウジマエ","name_h":"こうちようじまえ","name_e":"kouchiyoujimae"},{"bank_code":"6345","code":"015","name":"西浦みかん","name_k":"ニシウラミカン","name_h":"にしうらみかん","name_e":"nishiuramikan"},{"bank_code":"6345","code":"017","name":"山王通り","name_k":"サンノウドオリ","name_h":"さんのうどおり","name_e":"san'noudoori"},{"bank_code":"6345","code":"018","name":"沼津","name_k":"ヌマヅ","name_h":"ぬまづ","name_e":"numadu"},{"bank_code":"6345","code":"021","name":"片浜","name_k":"カタハマ","name_h":"かたはま","name_e":"katahama"},{"bank_code":"6345","code":"031","name":"清水","name_k":"シミズ","name_h":"しみず","name_e":"shimizu"},{"bank_code":"6345","code":"032","name":"徳倉","name_k":"トクラ","name_h":"とくら","name_e":"tokura"},{"bank_code":"6345","code":"034","name":"長沢","name_k":"ナガサワ","name_h":"ながさわ","name_e":"nagasawa"},{"bank_code":"6345","code":"051","name":"長泉","name_k":"ナガイズミ","name_h":"ながいずみ","name_e":"nagaizumi"},{"bank_code":"6345","code":"052","name":"下土狩","name_k":"シモトガリ","name_h":"しもとがり","name_e":"shimotogari"},{"bank_code":"6345","code":"054","name":"東","name_k":"ヒガシ","name_h":"ひがし","name_e":"higashi"},{"bank_code":"6345","code":"055","name":"中土狩","name_k":"ナカトガリ","name_h":"なかとがり","name_e":"nakatogari"},{"bank_code":"6345","code":"056","name":"納米里","name_k":"ナメリ","name_h":"なめり","name_e":"nameri"},{"bank_code":"6345","code":"061","name":"富岡","name_k":"トミオカ","name_h":"とみおか","name_e":"tomioka"},{"bank_code":"6345","code":"062","name":"裾野西","name_k":"スソノニシ","name_h":"すそのにし","name_e":"susononishi"},{"bank_code":"6345","code":"063","name":"泉","name_k":"イズミ","name_h":"いずみ","name_e":"izumi"},{"bank_code":"6345","code":"064","name":"深良","name_k":"フカラ","name_h":"ふから","name_e":"fukara"},{"bank_code":"6345","code":"065","name":"須山","name_k":"スヤマ","name_h":"すやま","name_e":"suyama"},{"bank_code":"6345","code":"080","name":"本店","name_k":"ホンテン","name_h":"ほんてん","name_e":"honten"}]