[{"code":"010","name":"洲本","name_k":"スモト","name_h":"すもと","name_e":"sumoto"},{"code":"020","name":"津名","name_k":"ツナ","name_h":"つな","name_e":"tsuna"},{"code":"025","name":"生穂","name_k":"イクホ","name_h":"いくほ","name_e":"ikuho"},{"code":"030","name":"東浦淡路","name_k":"ヒガシウラアワジ","name_h":"ひがしうらあわじ","name_e":"higashiuraawaji"},{"code":"033","name":"岩屋","name_k":"イワヤ","name_h":"いわや","name_e":"iwaya"},{"code":"050","name":"北淡","name_k":"ホクダン","name_h":"ほくだん","name_e":"hokudan"},{"code":"056","name":"育波","name_k":"イクハ","name_h":"いくは","name_e":"ikuha"},{"code":"060","name":"一宮","name_k":"イチノミヤ","name_h":"いちのみや","name_e":"ichinomiya"},{"code":"070","name":"鮎原","name_k":"アイハラ","name_h":"あいはら","name_e":"aihara"},{"code":"071","name":"都志","name_k":"ツシ","name_h":"つし","name_e":"tsushi"},{"code":"072","name":"五色丘","name_k":"ゴシキオカ","name_h":"ごしきおか","name_e":"goshikioka"},{"code":"100","name":"本店","name_k":"ホンテン","name_h":"ほんてん","name_e":"honten"}]