[{"code":"001","name":"本所","name_k":"ホンシヨ","name_h":"ほんしよ","name_e":"honshiyo"},{"code":"010","name":"石井","name_k":"イシイ","name_h":"いしい","name_e":"ishii"},{"code":"020","name":"浦庄","name_k":"ウラシヨウ","name_h":"うらしよう","name_e":"urashiyou"},{"code":"030","name":"高原","name_k":"タカハラ","name_h":"たかはら","name_e":"takahara"},{"code":"040","name":"藍畑","name_k":"アイハタ","name_h":"あいはた","name_e":"aihata"},{"code":"050","name":"高川原","name_k":"タカガワラ","name_h":"たかがわら","name_e":"takagawara"},{"code":"102","name":"広野","name_k":"ヒロノ","name_h":"ひろの","name_e":"hirono"},{"code":"103","name":"阿川","name_k":"アガワ","name_h":"あがわ","name_e":"agawa"},{"code":"104","name":"鬼籠野","name_k":"オロノ","name_h":"おろの","name_e":"orono"},{"code":"105","name":"神領","name_k":"ジンリヨウ","name_h":"じんりよう","name_e":"jinriyou"},{"code":"106","name":"神山","name_k":"カミヤマ","name_h":"かみやま","name_e":"kamiyama"},{"code":"107","name":"下分","name_k":"シモブン","name_h":"しもぶん","name_e":"shimobun"},{"code":"108","name":"上分","name_k":"カミブン","name_h":"かみぶん","name_e":"kamibun"}]