[{"bank_code":"8715","code":"001","name":"本所","name_k":"ホンシヨ","name_h":"ほんしよ","name_e":"honshiyo"},{"bank_code":"8715","code":"002","name":"大任","name_k":"オオトウ","name_h":"おおとう","name_e":"ootou"},{"bank_code":"8715","code":"003","name":"川崎","name_k":"カワサキ","name_h":"かわさき","name_e":"kawasaki"},{"bank_code":"8715","code":"004","name":"伊田","name_k":"イタ","name_h":"いた","name_e":"ita"},{"bank_code":"8715","code":"005","name":"後藤寺","name_k":"ゴトウジ","name_h":"ごとうじ","name_e":"gotouji"},{"bank_code":"8715","code":"006","name":"猪位金","name_k":"イイカネ","name_h":"いいかね","name_e":"iikane"},{"bank_code":"8715","code":"007","name":"方城","name_k":"ホウジヨウ","name_h":"ほうじよう","name_e":"houjiyou"},{"bank_code":"8715","code":"008","name":"金田","name_k":"カナダ","name_h":"かなだ","name_e":"kanada"},{"bank_code":"8715","code":"009","name":"赤池","name_k":"アカイケ","name_h":"あかいけ","name_e":"akaike"},{"bank_code":"8715","code":"010","name":"糸田","name_k":"イトダ","name_h":"いとだ","name_e":"itoda"},{"bank_code":"8715","code":"011","name":"安真木出張所","name_k":"アマギ","name_h":"あまぎ","name_e":"amagi"},{"bank_code":"8715","code":"012","name":"弁城出張所","name_k":"ベンジヨウ","name_h":"べんじよう","name_e":"benjiyou"},{"bank_code":"8715","code":"013","name":"市場出張所","name_k":"イチバ","name_h":"いちば","name_e":"ichiba"},{"bank_code":"8715","code":"014","name":"金川","name_k":"カナガワ","name_h":"かながわ","name_e":"kanagawa"},{"bank_code":"8715","code":"015","name":"添田","name_k":"ソエダ","name_h":"そえだ","name_e":"soeda"},{"bank_code":"8715","code":"017","name":"彦山出張所","name_k":"ヒコサン","name_h":"ひこさん","name_e":"hikosan"},{"bank_code":"8715","code":"018","name":"津野出張所","name_k":"ツノ","name_h":"つの","name_e":"tsuno"},{"bank_code":"8715","code":"019","name":"採銅所","name_k":"サイドウシヨ","name_h":"さいどうしよ","name_e":"saidoushiyo"},{"bank_code":"8715","code":"020","name":"高野","name_k":"タカノ","name_h":"たかの","name_e":"takano"},{"bank_code":"8715","code":"021","name":"香春出張所","name_k":"カワラ","name_h":"かわら","name_e":"kawara"},{"bank_code":"8715","code":"022","name":"赤","name_k":"アカ","name_h":"あか","name_e":"aka"}]